Workbook

Sheet Liste usagers 2025
K1: Gestion et temporalité | P1: Origine et nature de la demande | T1: Traitement apporté
A2: N° de dossier | B2: Nom | C2: Prénom | D2: Genre | E2: Tranche d'âge | F2: Adresse | G2: N° | H2: Secteur | I2: N°de téléphone | J2: Adresse mail | K2: Titulaire | L2: Date de reception | M2: Date d'ouverture | N2: Delai de traitement | O2: Date de clôture | P2: Type de conflit | Q2: Autre type de conflit | R2: Envoyeur | S2: Autres | T2: Partenaire | U2: Autres | V2: Type de médiation | W2: Orientation | X2: Autres | Y2: Statut | Z2: Issue
A3: 1 | B3: Wester | C3: Théo | D3: Homme | E3: 30 - 50 ans | F3: Avenue Docteur Zamenhof | G3: 2/164 | H3: =IFERROR(VLOOKUP(F3, Index!C:D, 2, FALSE), "") -> Vaillance | I3: 0476/893403 | J3: theo.wester@gmail.com | K3: Louise | L3: 45663 | M3: 45663 | N3: =IF(OR(L3="", M3=""), "", IF(L3=M3, 1, M3 - L3)) -> 1 | O3: 45665 | P3: Conflits Locatifs | R3: Demande spontanée | T3: Autre | U3: PILDA | V3: Individuelle | W3: Autre | X3: PILDA | Y3: Clôturé | Z3: Réorientation
A4: 2 | B4: Grami | C4: Wannes | D4: Homme | E4: 30 - 50 ans | F4: Chaussée de Ninove 623-739 /700-788 | G4: 707 | H4: =IFERROR(VLOOKUP(F4, Index!C:D, 2, FALSE), "") -> Peterbos | I4: 0486/939870 | K4: Pascal | L4: 45666 | M4: 45671 | N4: =IF(OR(L4="", M4=""), "", IF(L4=M4, 1, M4 - L4)) -> 5 | O4: 45770 | P4: Copropriété | R4: ULAC | V4: Individuelle | Y4: Clôturé | Z4: Apaisement
A5: 3 | B5: Gambier | C5: Manon | D5: Femme | E5: 18 - 30 ans | F5: Rue Georges Moreau | G5: 190 | H5: =IFERROR(VLOOKUP(F5, Index!C:D, 2, FALSE), "") -> Cureghem | I5: 33663775606 | J5: manongambier95@gmail.com | K5: Pascal | L5: 45664 | M5: 45666 | N5: =IF(OR(L5="", M5=""), "", IF(L5=M5, 1, M5 - L5)) -> 2 | O5: 45692 | P5: Conflits de voisinage | Q5: nuisances sonores | R5: Déjà venu | T5: Autre | U5: Ecole St Pierre | V5: Individuelle | Y5: Clôturé | Z5: Refus (de l'une partie ou des deux)
A6: 4 | B6: Sibide | C6: Fatoumata | D6: Femme | H6: =IFERROR(VLOOKUP(F6, Index!C:D, 2, FALSE), "") | J6: diakiteadma113@gmail.com | K6: Pascal | L6: 45646 | M6: 45659 | N6: =IF(OR(L6="", M6=""), "", IF(L6=M6, 1, M6 - L6)) -> 13 | P6: Conflits Locatifs | R6: Demande spontanée | V6: Individuelle | Y6: Clôturé | Z6: Impossibilité technique (non-joignables)
A7: 5 | B7: Rouyer | C7: Emma | D7: Femme | E7: 30 - 50 ans | H7: =IFERROR(VLOOKUP(F7, Index!C:D, 2, FALSE), "") | I7: 0485/398629 | J7: emma_zebr@yahoo.fr | K7: Pascal | L7: 45644 | M7: 45666 | N7: =IF(OR(L7="", M7=""), "", IF(L7=M7, 1, M7 - L7)) -> 22 | O7: 45749 | P7: Autres conflits | Q7: Entre artistes (propriété intellectuelle) | R7: Déjà venu | T7: TSR | V7: Individuelle | W7: Autre | X7: Avocat | Y7: Clôturé | Z7: Refus (de l'une partie ou des deux)
A8: 6 | B8: Van Saene | C8: David | D8: Homme | E8: 30 - 50 ans | F8: Avenue Eugène Ysaÿe | G8: 105 | H8: =IFERROR(VLOOKUP(F8, Index!C:D, 2, FALSE), "") -> Parc | I8: 0486/510427 | K8: Pascal | L8: 45639 | M8: 45660 | N8: =IF(OR(L8="", M8=""), "", IF(L8=M8, 1, M8 - L8)) -> 21 | O8: 45666 | P8: Conflits de voisinage | Q8: nuisances sonores | R8: Déjà venu | V8: Individuelle | Y8: Clôturé | Z8: Apaisement
A9: 7 | B9: Benayad | C9: Abdellatif | D9: Homme | F9: Rue de Douvres | G9: 26 | H9: =IFERROR(VLOOKUP(F9, Index!C:D, 2, FALSE), "") -> Vaillance | I9: 0495777585 | J9: renovaben@yahoo.fr | K9: Pascal | L9: 45642 | M9: 45665 | N9: =IF(OR(L9="", M9=""), "", IF(L9=M9, 1, M9 - L9)) -> 23 | P9: Conflits de voisinage | R9: Demande spontanée | V9: Individuelle | Y9: Clôturé | Z9: Impossibilité technique (non-joignables)
A10: 8 | B10: Carvalho | C10: Daniel | D10: Homme | E10: 30 - 50 ans | F10: ADRESSE | H10: =IFERROR(VLOOKUP(F10, Index!C:D, 2, FALSE), "") -> SECTEUR | I10: 0494831519 | J10: dani.vdc@live.com | K10: Sedia | L10: 45664 | M10: 45664 | N10: =IF(OR(L10="", M10=""), "", IF(L10=M10, 1, M10 - L10)) -> 1 | O10: 45665 | P10: Conflits de voisinage | R10: Demande spontanée | V10: Individuelle | Y10: Clôturé | Z10: Refus (de l'une partie ou des deux)
A11: 9 | D11: Femme | E11: 50 ans et + | F11: Rue Buffon | H11: =IFERROR(VLOOKUP(F11, Index!C:D, 2, FALSE), "") -> Peterbos | K11: Louise | L11: 45663 | M11: 45663 | N11: =IF(OR(L11="", M11=""), "", IF(L11=M11, 1, M11 - L11)) -> 1 | O11: 45713 | P11: Conflits de voisinage | Q11: arbre | R11: Demande spontanée | V11: Individuelle | Y11: Clôturé | Z11: Impossibilité technique (non-joignables)
A12: 10 | D12: Homme | E12: 30 - 50 ans | F12: Square de l'Aviation | G12: 28 | H12: =IFERROR(VLOOKUP(F12, Index!C:D, 2, FALSE), "") -> Cureghem | K12: Louise | L12: 45664 | M12: 45664 | N12: =IF(OR(L12="", M12=""), "", IF(L12=M12, 1, M12 - L12)) -> 1 | O12: 45713 | P12: Conflits de voisinage | Q12: nuisances sonores | R12: Demande spontanée | V12: Individuelle | Y12: Clôturé | Z12: Impossibilité technique (non-joignables)
A13: 11 | B13: Adakaev | D13: Homme | F13: ADRESSE | H13: =IFERROR(VLOOKUP(F13, Index!C:D, 2, FALSE), "") -> SECTEUR | J13: adakaev@outlook.com | K13: Louise | L13: 45664 | M13: 45664 | N13: =IF(OR(L13="", M13=""), "", IF(L13=M13, 1, M13 - L13)) -> 1 | O13: 45664 | P13: Autres conflits | Q13: stationnement | R13: Demande spontanée | V13: Individuelle | W13: Autre | X13: SAC | Y13: Clôturé | Z13: Réorientation
A14: 12 | B14: Cesatti | C14: Nellio | D14: Homme | E14: 30 - 50 ans | F14: Place Henri De Smet | G14: 1 | H14: =IFERROR(VLOOKUP(F14, Index!C:D, 2, FALSE), "") -> Scheut | I14: 0474/76 57 80 | K14: Louise | L14: 45666 | M14: 45671 | N14: =IF(OR(L14="", M14=""), "", IF(L14=M14, 1, M14 - L14)) -> 5 | O14: 45939 | P14: Conflits de voisinage | R14: Demande spontanée | V14: Individuelle | W14: TSR | X14: Amine | Y14: Clôturé | Z14: Réorientation
A15: 13 | B15: Bulambo | C15: Dunia | D15: Homme | E15: 30 - 50 ans | F15: Rue de l'Orphelinat | G15: 33 | H15: =IFERROR(VLOOKUP(F15, Index!C:D, 2, FALSE), "") -> Scheut | I15: 0493/46 24 12 | K15: Pascal | L15: 45673 | M15: 45673 | N15: =IF(OR(L15="", M15=""), "", IF(L15=M15, 1, M15 - L15)) -> 1 | O15: 45761 | P15: Conflits de voisinage | R15: Déjà venu | T15: Police | V15: Individuelle | Y15: Clôturé | Z15: Interruption du processus de médiation
A16: 14 | B16: antagana | C16: sandrine | D16: Femme | E16: 30 - 50 ans | F16: ADRESSE | H16: =IFERROR(VLOOKUP(F16, Index!C:D, 2, FALSE), "") -> SECTEUR | I16: 0465275893 | J16: tang.ana@outlook.com | K16: Sedia | L16: 45665 | M16: 45665 | N16: =IF(OR(L16="", M16=""), "", IF(L16=M16, 1, M16 - L16)) -> 1 | O16: 45665 | P16: Conflits Locatifs | Q16: état des lieux | R16: Demande spontanée | V16: Individuelle | Y16: Clôturé | Z16: Refus (de l'une partie ou des deux)
A17: 15 | B17: Cenem | C17: Alexandre | D17: Homme | E17: 30 - 50 ans | F17: ADRESSE | H17: =IFERROR(VLOOKUP(F17, Index!C:D, 2, FALSE), "") -> SECTEUR | I17: 0478357132 | K17: Sedia | L17: 45664 | M17: 45672 | N17: =IF(OR(L17="", M17=""), "", IF(L17=M17, 1, M17 - L17)) -> 8 | O17: 45672 | P17: Conflits Familiaux/ Conjugaux | Q17: separation garde de l enfant | R17: Demande spontanée | V17: Individuelle | Y17: Clôturé | Z17: Réorientation
A18: 16 | B18: lawniczak | C18: marlon | D18: Femme | F18: ADRESSE | H18: =IFERROR(VLOOKUP(F18, Index!C:D, 2, FALSE), "") -> SECTEUR | I18: 0456752606 | K18: Sedia | L18: 45660 | M18: 45660 | N18: =IF(OR(L18="", M18=""), "", IF(L18=M18, 1, M18 - L18)) -> 1 | O18: 45965 | P18: Conflits Familiaux/ Conjugaux | Q18: garde enfant | R18: Demande spontanée | V18: Individuelle | Y18: Clôturé | Z18: Refus (de l'une partie ou des deux)
A19: 17 | B19: Almi | C19: El hassan | D19: Homme | E19: 30 - 50 ans | F19: ADRESSE | H19: =IFERROR(VLOOKUP(F19, Index!C:D, 2, FALSE), "") -> SECTEUR | I19: 0486087344 | J19: slaama@abcoop.be | K19: Sedia | L19: 45673 | M19: 45673 | N19: =IF(OR(L19="", M19=""), "", IF(L19=M19, 1, M19 - L19)) -> 1 | P19: Conflits de voisinage | R19: Demande spontanée | V19: Individuelle | Y19: Clôturé
A20: 18 | B20: Benatia | C20: mohamed | D20: Homme | E20: 50 ans et + | F20: ADRESSE | H20: =IFERROR(VLOOKUP(F20, Index!C:D, 2, FALSE), "") -> SECTEUR | I20: 0487447501 | K20: Sedia | L20: 45665 | M20: 45665 | N20: =IF(OR(L20="", M20=""), "", IF(L20=M20, 1, M20 - L20)) -> 1 | O20: 45665 | P20: Autres conflits | Q20: conflit avec infor sourd | R20: Demande spontanée | V20: Individuelle | Y20: Clôturé | Z20: Réorientation
A21: 19 | D21: Femme | E21: 50 ans et + | F21: Avenue de la Libre Académie | G21: 72 | H21: =IFERROR(VLOOKUP(F21, Index!C:D, 2, FALSE), "") -> Parc | K21: Louise | L21: 45685 | M21: 45685 | N21: =IF(OR(L21="", M21=""), "", IF(L21=M21, 1, M21 - L21)) -> 1 | O21: 45685 | P21: Conflits Locatifs | R21: Justice de Paix | S21: permanence | V21: Individuelle | Y21: Clôturé | Z21: Accord écrit
A22: 20 | D22: Femme | E22: 50 ans et + | F22: ADRESSE | H22: =IFERROR(VLOOKUP(F22, Index!C:D, 2, FALSE), "") -> SECTEUR | K22: Louise | L22: 45685 | M22: 45685 | N22: =IF(OR(L22="", M22=""), "", IF(L22=M22, 1, M22 - L22)) -> 1 | O22: 45685 | P22: Conflits Locatifs | R22: Justice de Paix | S22: permanence | V22: Individuelle | W22: Justice de Paix | Y22: Clôturé | Z22: Réorientation
A23: 21 | B23: Nasir | C23: Warsan | D23: Femme | E23: 30 - 50 ans | F23: Rue des Goujons | G23: 59 | H23: =IFERROR(VLOOKUP(F23, Index!C:D, 2, FALSE), "") -> Cureghem | I23: 0465/662462 | K23: Louise | L23: 45694 | M23: 45694 | N23: =IF(OR(L23="", M23=""), "", IF(L23=M23, 1, M23 - L23)) -> 1 | O23: 45715 | P23: Conflits de voisinage | R23: Demande spontanée | V23: Individuelle | Y23: Clôturé | Z23: Impossibilité technique (non-joignables)
A24: 22 | B24: Genkhang | C24: Rigzin | D24: Femme | E24: 50 ans et + | F24: Avenue du Roi Soldat | G24: 11 | H24: =IFERROR(VLOOKUP(F24, Index!C:D, 2, FALSE), "") -> Parc | I24: 0474995189 | J24: himalayancraft4you@gmail.com | K24: Sedia | L24: 45693 | M24: 45694 | N24: =IF(OR(L24="", M24=""), "", IF(L24=M24, 1, M24 - L24)) -> 1 | P24: Conflits de voisinage | Q24: nuisances sonores | R24: Demande spontanée | V24: Individuelle | Y24: Clôturé | Z24: Apaisement
A25: 23 | B25: Kenf | C25: Benedicte | D25: Femme | E25: 30 - 50 ans | F25: Avenue d'Itterbeek | G25: 121 | H25: =IFERROR(VLOOKUP(F25, Index!C:D, 2, FALSE), "") -> Neerpede | K25: Louise | L25: 45693 | M25: 45694 | N25: =IF(OR(L25="", M25=""), "", IF(L25=M25, 1, M25 - L25)) -> 1 | O25: 45876 | P25: Cohabitation/colocation | R25: Demande spontanée | V25: Individuelle | W25: Justice de Paix | Y25: Clôturé | Z25: Réorientation
A26: 24 | B26: Amyay | C26: Abdelaziz | D26: Homme | E26: 50 ans et + | F26: Rue Victor Rauter | G26: 185 | H26: =IFERROR(VLOOKUP(F26, Index!C:D, 2, FALSE), "") -> Vaillance | I26: 0487/531305 | K26: Louise | L26: 45694 | M26: 45694 | N26: =IF(OR(L26="", M26=""), "", IF(L26=M26, 1, M26 - L26)) -> 1 | O26: 45876 | P26: Conflits de voisinage | R26: Demande spontanée | V26: Individuelle | Y26: Clôturé | Z26: Refus (de l'une partie ou des deux)
A27: 25 | B27: Sanciaume | C27: Luc | D27: Homme | E27: 30 - 50 ans | F27: Rue de Veeweyde | G27: 29 | H27: =IFERROR(VLOOKUP(F27, Index!C:D, 2, FALSE), "") -> Vaillance | I27: 0471/36 58 15 | K27: Louise | L27: 45698 | M27: 45698 | N27: =IF(OR(L27="", M27=""), "", IF(L27=M27, 1, M27 - L27)) -> 1 | O27: 45876 | P27: Conflits de voisinage | R27: Demande spontanée | V27: Individuelle | Y27: Clôturé | Z27: Impossibilité technique (non-joignables)
A28: 26 | B28: D'Ostunx | C28: cathy | D28: Femme | E28: 30 - 50 ans | H28: =IFERROR(VLOOKUP(F28, Index!C:D, 2, FALSE), "") | I28: 0495498855 | K28: Sedia | L28: 45706 | M28: 45706 | N28: =IF(OR(L28="", M28=""), "", IF(L28=M28, 1, M28 - L28)) -> 1 | O28: 45874 | P28: Conflits Familiaux/ Conjugaux | R28: Demande spontanée | V28: Individuelle | W28: Justice de Paix | Y28: Clôturé | Z28: Apaisement avant médiation
A29: 27 | B29: Fourneau | C29: olivier | D29: Homme | E29: 30 - 50 ans | F29: Rue Adolphe Willemyns | G29: 46 | H29: =IFERROR(VLOOKUP(F29, Index!C:D, 2, FALSE), "") -> Peterbos | I29: 0485794472 | K29: Pascal | L29: 45706 | M29: 45706 | N29: =IF(OR(L29="", M29=""), "", IF(L29=M29, 1, M29 - L29)) -> 1 | O29: 45758 | P29: Conflits de voisinage | Q29: mur mitoyen | R29: Justice de Paix | V29: Individuelle | Y29: Clôturé | Z29: Interruption du processus de médiation
A30: 28 | B30: Vanbroeck | C30: gretta | D30: Femme | E30: 30 - 50 ans | F30: Avenue Marius Renard | G30: 47 | H30: =IFERROR(VLOOKUP(F30, Index!C:D, 2, FALSE), "") -> Parc | I30: 0478637118 | K30: Sedia | L30: 45707 | M30: 45707 | N30: =IF(OR(L30="", M30=""), "", IF(L30=M30, 1, M30 - L30)) -> 1 | P30: Conflits de voisinage | Q30: nuisance sonore | R30: Justice de Paix | V30: Individuelle | Y30: Clôturé | Z30: Réorientation
A31: 29 | D31: Femme | E31: 50 ans et + | F31: Avenue Romain Rolland | G31: 87 | H31: =IFERROR(VLOOKUP(F31, Index!C:D, 2, FALSE), "") -> Parc | I31: 02/520 05 04 | K31: Louise | L31: 45698 | M31: 45713 | N31: 15 | O31: 45713 | P31: Autres conflits | Q31: proximus | R31: Demande spontanée | V31: Individuelle | Y31: Clôturé | Z31: Réorientation
A32: 30 | B32: Ouantis | C32: Ben Abdallah | D32: Homme | E32: 50 ans et + | F32: Clos des Asters | G32: 8A | H32: =IFERROR(VLOOKUP(F32, Index!C:D, 2, FALSE), "") -> La Roue | I32: 0489/85 34 95 | K32: Louise | L32: 45705 | M32: 45713 | N32: =IF(OR(L32="", M32=""), "", IF(L32=M32, 1, M32 - L32)) -> 8 | O32: 45939 | P32: Conflits de voisinage | R32: Autre | V32: Individuelle | Y32: Clôturé | Z32: Refus (de l'une partie ou des deux)
A33: 31 | B33: Waerzeggers | C33: Louis | D33: Homme | E33: 50 ans et + | F33: Avenue du Roi Soldat | G33: 34 | H33: =IFERROR(VLOOKUP(F33, Index!C:D, 2, FALSE), "") -> Parc | I33: 0474/61 61 26 | K33: Louise | L33: 45707 | M33: 45713 | N33: =IF(OR(L33="", M33=""), "", IF(L33=M33, 1, M33 - L33)) -> 6 | O33: 45713 | P33: Conflits de voisinage | Q33: arbre | R33: Autre | S33: espaces verts - commune | V33: Individuelle | Y33: Clôturé | Z33: Refus (de l'une partie ou des deux)
A34: 32 | B34: Kapp | C34: sebastien | D34: Homme | E34: 30 - 50 ans | F34: ADRESSE | H34: =IFERROR(VLOOKUP(F34, Index!C:D, 2, FALSE), "") -> SECTEUR | I34: 0487798816 | J34: seb_kapp@hotmail.com | K34: Sedia | L34: 45714 | M34: 45714 | N34: =IF(OR(L34="", M34=""), "", IF(L34=M34, 1, M34 - L34)) -> 1 | O34: 45902 | P34: Conflits Familiaux/ Conjugaux | Q34: divorce | R34: Demande spontanée | V34: Individuelle | Y34: Clôturé | Z34: Accord écrit
A35: 33 | B35: Neumans | C35: j-p | D35: Homme | E35: 50 ans et + | F35: ADRESSE | H35: =IFERROR(VLOOKUP(F35, Index!C:D, 2, FALSE), "") -> SECTEUR | I35: 0499939875 | K35: Sedia | L35: 45720 | M35: 45720 | N35: =IF(OR(L35="", M35=""), "", IF(L35=M35, 1, M35 - L35)) -> 1 | P35: Conflits Locatifs | Q35: garantie locative | R35: Demande spontanée | V35: Individuelle | Y35: Clôturé | Z35: Réorientation
A36: 34 | B36: Boly | C36: A | D36: Femme | E36: 30 - 50 ans | F36: Rue de Birmingham | G36: 300 | H36: =IFERROR(VLOOKUP(F36, Index!C:D, 2, FALSE), "") -> Scheut | I36: 0487646500 | J36: adiaratouboly@yahoo.fr | K36: Sedia | L36: 45720 | M36: 45720 | N36: =IF(OR(L36="", M36=""), "", IF(L36=M36, 1, M36 - L36)) -> 1 | P36: Conflits de voisinage | Q36: bruit enfant | R36: Demande spontanée | V36: Individuelle | Y36: Clôturé
A37: 35 | B37: Khabouchi | C37: Marwa | D37: Femme | E37: 30 - 50 ans | F37: Chaussée de Ninove 623-739 /700-788 | G37: 626 | H37: =IFERROR(VLOOKUP(F37, Index!C:D, 2, FALSE), "") -> Peterbos | I37: 0495/56 28 39 | K37: Louise | L37: 45708 | M37: 45713 | N37: =IF(OR(L37="", M37=""), "", IF(L37=M37, 1, M37 - L37)) -> 5 | O37: 45876 | P37: Conflits de voisinage | R37: Autre | S37: ASBL Après tout | V37: Individuelle | Y37: Clôturé | Z37: Refus (de l'une partie ou des deux)
A38: 36 | B38: sans nom | C38: propriétaire | D38: Femme | H38: =IFERROR(VLOOKUP(F38, Index!C:D, 2, FALSE), "") | I38: 0474472178 | K38: Sedia | L38: 45715 | M38: 45727 | N38: =IF(OR(L38="", M38=""), "", IF(L38=M38, 1, M38 - L38)) -> 12 | O38: 45965 | P38: Conflits de voisinage | R38: Demande spontanée | V38: Individuelle | Y38: Clôturé | Z38: Impossibilité technique (non-joignables)
A39: 37 | B39: sene | C39: elhadji | E39: 30 - 50 ans | F39: Rue des Goujons | H39: =IFERROR(VLOOKUP(F39, Index!C:D, 2, FALSE), "") -> Cureghem | I39: 0484161556 | K39: Sedia | L39: 45721 | M39: 45727 | N39: =IF(OR(L39="", M39=""), "", IF(L39=M39, 1, M39 - L39)) -> 6 | O39: 45965 | P39: Conflits de voisinage | Q39: bruit enfants | R39: Demande spontanée | V39: Individuelle | Y39: Clôturé | Z39: Interruption du processus de médiation
A40: 38 | B40: ercovier | C40: henri | D40: Homme | E40: 50 ans et + | F40: Avenue Tolstoï | G40: 3 | H40: =IFERROR(VLOOKUP(F40, Index!C:D, 2, FALSE), "") -> Peterbos | I40: 0496794180 | K40: Sedia | L40: 45728 | M40: 45728 | N40: =IF(OR(L40="", M40=""), "", IF(L40=M40, 1, M40 - L40)) -> 1 | O40: 45965 | P40: Conflits Familiaux/ Conjugaux | Q40: femme , enfants,amant | R40: Foyer Anderlechtois | V40: Individuelle | Y40: Clôturé | Z40: Interruption du processus de médiation
A41: 39 | B41: Bouthagane | C41: zora | D41: Femme | E41: 30 - 50 ans | F41: Rue des Goujons | H41: goujon | I41: 0496294427 | K41: Sedia | L41: 45728 | M41: 45728 | N41: =IF(OR(L41="", M41=""), "", IF(L41=M41, 1, M41 - L41)) -> 1 | P41: Conflits de voisinage | Q41: bruit enfants | R41: Foyer Anderlechtois | V41: Individuelle | Y41: Clôturé
A42: 40 | B42: Baufays | C42: Francis | D42: Homme | E42: 50 ans et + | F42: Avenue Frans Van Kalken | G42: 14 | H42: =IFERROR(VLOOKUP(F42, Index!C:D, 2, FALSE), "") -> Vaillance | I42: 02/523 18 67 | K42: Pascal | L42: 45735 | M42: 45958 | N42: =IF(OR(L42="", M42=""), "", IF(L42=M42, 1, M42 - L42)) -> 223 | O42: 45810 | P42: Conflits de voisinage | Q42: bruits voisins du dessus | R42: Autre | S42: Cabinet Miroir | V42: Individuelle | Y42: Clôturé | Z42: Apaisement avant médiation
A43: 41 | B43: Ladia | C43: alexia | D43: Femme | E43: 50 ans et + | F43: ADRESSE | H43: =IFERROR(VLOOKUP(F43, Index!C:D, 2, FALSE), "") -> SECTEUR | I43: 0486366409 | K43: Sedia | L43: 45734 | N43: =IF(OR(L43="", M43=""), "", IF(L43=M43, 1, M43 - L43)) | P43: Conflits Locatifs | Q43: non paiement loyer | R43: Justice de Paix | V43: Individuelle | W43: Justice de Paix | Y43: Clôturé
A44: 42 | B44: Chentouf | C44: Rachid | D44: Homme | E44: 30 - 50 ans | F44: Rue Docteur Kuborn | G44: 31 | H44: =IFERROR(VLOOKUP(F44, Index!C:D, 2, FALSE), "") -> Cureghem | I44: 0485/448303 | K44: Pascal | L44: 45725 | M44: 45727 | N44: =IF(OR(L44="", M44=""), "", IF(L44=M44, 1, M44 - L44)) -> 2 | O44: 45797 | P44: Conflits en lien avec l'espace public | Q44: saleté trottoir | R44: Autre | S44: Affiche | T44: Gardiens de la Paix | V44: Collective | W44: Gardiens de la Paix | Y44: Clôturé | Z44: Apaisement avant médiation
A45: 43 | B45: Servais | C45: Mireille | D45: Femme | E45: 30 - 50 ans | F45: Rue de l'Orphelinat | G45: 41 | H45: =IFERROR(VLOOKUP(F45, Index!C:D, 2, FALSE), "") -> Scheut | I45: 0473/540811 | J45: mireille@m11.be | K45: Pascal | L45: 45691 | M45: 45691 | N45: =IF(OR(L45="", M45=""), "", IF(L45=M45, 1, M45 - L45)) -> 1 | O45: 45748 | P45: Conflits Locatifs | Q45: non paiement loyer | R45: Demande spontanée | T45: Autre | U45: Expulsions | V45: Individuelle | W45: Autre | X45: Expulsions | Y45: Clôturé | Z45: Impossibilité technique (non-joignables)
A46: 44 | B46: Berg | C46: Ylva | D46: Femme | E46: 30 - 50 ans | F46: Rue Porselein | G46: 9 | H46: =IFERROR(VLOOKUP(F46, Index!C:D, 2, FALSE), "") -> Vaillance | I46: 0485/148446 | K46: Pascal | L46: 45717 | M46: 45717 | N46: =IF(OR(L46="", M46=""), "", IF(L46=M46, 1, M46 - L46)) -> 1 | O46: 45777 | P46: Conflits de voisinage | Q46: humidité mur mitoyen | R46: Demande spontanée | V46: Collective | Y46: Clôturé | Z46: Apaisement avant médiation
A47: 45 | B47: Mostinckx | C47: Robbe | D47: Femme | E47: 30 - 50 ans | F47: Rue Saint-Guidon | H47: =IFERROR(VLOOKUP(F47, Index!C:D, 2, FALSE), "") -> Vaillance | K47: Pascal | L47: 45741 | M47: 45741 | N47: =IF(OR(L47="", M47=""), "", IF(L47=M47, 1, M47 - L47)) -> 1 | P47: Conflits de voisinage | Q47: humidité mur mitoyen | R47: Justice de Paix | T47: Justice de Paix | V47: Individuelle | Y47: Clôturé | Z47: Accord verbal
A48: 46 | B48: Tramara | C48: Isabelle | D48: Femme | E48: 50 ans et + | F48: Rue de l'Agrément | G48: 4 | H48: =IFERROR(VLOOKUP(F48, Index!C:D, 2, FALSE), "") -> Peterbos | K48: Pascal | L48: 45740 | M48: 45740 | N48: =IF(OR(L48="", M48=""), "", IF(L48=M48, 1, M48 - L48)) -> 1 | O48: 45775 | P48: Conflits Locatifs | Q48: conflit propriétaire | R48: Déjà venu | V48: Individuelle | Y48: Clôturé | Z48: Apaisement avant médiation
A49: 47 | B49: Lorman | C49: Jean-Marie | D49: Homme | E49: 50 ans et + | F49: Rue Porselein | G49: 6 | H49: =IFERROR(VLOOKUP(F49, Index!C:D, 2, FALSE), "") -> Vaillance | I49: 0478/293287 | K49: Pascal | L49: 45695 | M49: 45695 | N49: =IF(OR(L49="", M49=""), "", IF(L49=M49, 1, M49 - L49)) -> 1 | O49: 45770 | P49: Conflits de voisinage | Q49: humidité mur mitoyen | R49: Déjà venu | V49: Individuelle | Y49: Clôturé | Z49: Accord verbal
A50: 48 | B50: Beaufays | D50: Homme | E50: 50 ans et + | F50: Avenue Frans Van Kalken | G50: 65 | H50: =IFERROR(VLOOKUP(F50, Index!C:D, 2, FALSE), "") -> Vaillance | I50: 0479/060187 | K50: Pascal | L50: 45735 | M50: 45744 | N50: =IF(OR(L50="", M50=""), "", IF(L50=M50, 1, M50 - L50)) -> 9 | O50: 45810 | P50: Conflits de voisinage | Q50: bruit | R50: Demande spontanée | V50: Individuelle | Y50: Clôturé | Z50: Apaisement avant médiation
A51: 49 | B51: Lardinois | D51: Femme | E51: 50 ans et + | H51: La Roue | I51: 0475/342189 | K51: Pascal | L51: 45733 | M51: 45733 | N51: =IF(OR(L51="", M51=""), "", IF(L51=M51, 1, M51 - L51)) -> 1 | O51: 45764 | P51: Autres conflits | Q51: Dettes entre amis | R51: Déjà venu | V51: Individuelle | Y51: Clôturé | Z51: Interruption du processus de médiation
A52: 50 | B52: Boyker | D52: Homme | E52: 30 - 50 ans | F52: Boulevard Sylvain Dupuis | G52: 110 | H52: =IFERROR(VLOOKUP(F52, Index!C:D, 2, FALSE), "") -> Peterbos | I52: 0478/549425 | K52: Pascal | L52: 45702 | M52: 45702 | N52: =IF(OR(L52="", M52=""), "", IF(L52=M52, 1, M52 - L52)) -> 1 | O52: 45744 | P52: Conflits de voisinage | Q52: bruit/agressivité | R52: Déjà venu | V52: Individuelle | Y52: Clôturé | Z52: Réorientation
A53: 51 | B53: El Belkhiri | D53: Femme | E53: 18 - 30 ans | F53: Rue Bissé | G53: 17 | H53: =IFERROR(VLOOKUP(F53, Index!C:D, 2, FALSE), "") -> Cureghem | I53: 0484/172026 | K53: Pascal | L53: 45719 | M53: 45730 | N53: =IF(OR(L53="", M53=""), "", IF(L53=M53, 1, M53 - L53)) -> 11 | O53: 45743 | P53: Autres conflits | Q53: litige vente immeuble | R53: Déjà venu | V53: Individuelle | Y53: Clôturé | Z53: Refus (de l'une partie ou des deux)
A54: 52 | B54: Juan | D54: Homme | E54: 30 - 50 ans | H54: =IFERROR(VLOOKUP(F54, Index!C:D, 2, FALSE), "") | I54: 0491/284212 | K54: Louise & Pascal | L54: 45695 | M54: 45702 | N54: =IF(OR(L54="", M54=""), "", IF(L54=M54, 1, M54 - L54)) -> 7 | O54: 45748 | P54: Conflits Familiaux/ Conjugaux | R54: CAW Westland | T54: CAW Westland | V54: Individuelle | Y54: Clôturé | Z54: Refus (de l'une partie ou des deux)
A55: 53 | B55: Nafie | D55: Homme | E55: 30 - 50 ans | H55: =IFERROR(VLOOKUP(F55, Index!C:D, 2, FALSE), "") | K55: Pascal | L55: 45726 | M55: 45726 | N55: =IF(OR(L55="", M55=""), "", IF(L55=M55, 1, M55 - L55)) -> 1 | O55: 45748 | P55: Conflits de voisinage | Q55: Santé mentale | R55: Service Social de Cureghem | V55: Individuelle | Y55: Clôturé | Z55: Impossibilité technique (non-joignables)
A56: 54 | B56: Voïka | C56: Constantin | D56: Homme | E56: 30 - 50 ans | H56: =IFERROR(VLOOKUP(F56, Index!C:D, 2, FALSE), "") | I56: 0465/804047 | K56: Pascal | L56: 45688 | M56: 45692 | N56: =IF(OR(L56="", M56=""), "", IF(L56=M56, 1, M56 - L56)) -> 4 | O56: 45748 | P56: Conflits de voisinage | V56: Individuelle | Y56: Clôturé | Z56: Impossibilité technique (non-joignables)
A57: 55 | B57: Lambert | C57: Isabelle | D57: Femme | E57: 30 - 50 ans | H57: =IFERROR(VLOOKUP(F57, Index!C:D, 2, FALSE), "") | I57: 0474/770709 | K57: Pascal | L57: 45691 | M57: 45691 | N57: =IF(OR(L57="", M57=""), "", IF(L57=M57, 1, M57 - L57)) -> 1 | O57: 45748 | P57: Conflits Familiaux/ Conjugaux | V57: Individuelle | Y57: Clôturé | Z57: Refus (de l'une partie ou des deux)
A58: 56 | B58: Lejeune | D58: Homme | E58: 30 - 50 ans | F58: Avenue Paul Janson | G58: 76 | H58: =IFERROR(VLOOKUP(F58, Index!C:D, 2, FALSE), "") -> Vaillance | I58: 0474/472178 | K58: Pascal | L58: 45720 | M58: 45720 | N58: =IF(OR(L58="", M58=""), "", IF(L58=M58, 1, M58 - L58)) -> 1 | O58: 45728 | P58: Conflits Locatifs | T58: TSR | V58: Individuelle | Y58: Clôturé | Z58: Impossibilité technique (non-joignables)
A59: 57 | B59: De Haze | D59: Femme | E59: 30 - 50 ans | F59: Rue Docteur De Meersman | G59: 17 | H59: =IFERROR(VLOOKUP(F59, Index!C:D, 2, FALSE), "") -> Cureghem | I59: 0489/240486 | K59: Pascal | L59: 45691 | M59: 45691 | N59: =IF(OR(L59="", M59=""), "", IF(L59=M59, 1, M59 - L59)) -> 1 | O59: 45700 | P59: Conflits de voisinage | Q59: odeurs | R59: Autre | S59: Logmt pour Tous | V59: Individuelle | Y59: Clôturé | Z59: Refus (de l'une partie ou des deux)
A60: 58 | B60: Al Lamaakchaoui | C60: Ayoub | D60: Homme | E60: 30 - 50 ans | F60: Chaussée de Mons 1-153/2-154 | H60: =IFERROR(VLOOKUP(F60, Index!C:D, 2, FALSE), "") -> Cureghem | I60: 0465/379770 | J60: ayoub.brxl.be@gmail.com | K60: Pascal | L60: 45680 | M60: 45680 | N60: =IF(OR(L60="", M60=""), "", IF(L60=M60, 1, M60 - L60)) -> 1 | O60: 45707 | P60: Conflits de voisinage | Q60: odeurs/hygiène | R60: Demande spontanée | T60: CRIPA | V60: Individuelle | W60: CRIPA | Y60: Clôturé | Z60: Refus (de l'une partie ou des deux)
A61: 59 | B61: Muraru | C61: Constantin | D61: Homme | E61: 30 - 50 ans | F61: Rue Van Soust | H61: =IFERROR(VLOOKUP(F61, Index!C:D, 2, FALSE), "") -> Peterbos | K61: Pascal | L61: 45681 | M61: 45691 | N61: =IF(OR(L61="", M61=""), "", IF(L61=M61, 1, M61 - L61)) -> 10 | O61: 45707 | P61: Conflits de voisinage | Q61: odeurs cigarettes | R61: Demande spontanée | V61: Individuelle | Y61: Clôturé | Z61: Impossibilité technique (non-joignables)
A62: 60 | B62: Boualali | D62: Femme | E62: 30 - 50 ans | H62: =IFERROR(VLOOKUP(F62, Index!C:D, 2, FALSE), "") | I62: 0484/081245 | K62: Pascal | L62: 45693 | M62: 45693 | N62: =IF(OR(L62="", M62=""), "", IF(L62=M62, 1, M62 - L62)) -> 1 | O62: 45700 | P62: Autres conflits | Q62: litige financier associé | R62: Demande spontanée | V62: Individuelle | Y62: Clôturé | Z62: Impossibilité technique (non-joignables)
A63: 61 | B63: Tsalikidis | C63: Hélène | D63: Femme | E63: 30 - 50 ans | F63: Rue de l'Energie | G63: 38 | H63: =IFERROR(VLOOKUP(F63, Index!C:D, 2, FALSE), "") -> La Roue | I63: 0473/698417 | K63: Pascal | L63: 45747 | M63: 45747 | N63: =IF(OR(L63="", M63=""), "", IF(L63=M63, 1, M63 - L63)) -> 1 | O63: 45784 | P63: Conflits Locatifs | Q63: comportement locataire | R63: Justice de Paix | T63: Justice de Paix | V63: Individuelle | Y63: Clôturé | Z63: Accord verbal
A64: 62 | B64: Benatia | C64: ahmed | D64: Homme | E64: 50 ans et + | F64: ADRESSE | H64: =IFERROR(VLOOKUP(F64, Index!C:D, 2, FALSE), "") -> SECTEUR | I64: 0472172609 | K64: Sedia | L64: 45749 | M64: 45749 | N64: =IF(OR(L64="", M64=""), "", IF(L64=M64, 1, M64 - L64)) -> 1 | O64: 45749 | P64: Autres conflits | Q64: conflit avec son AS | R64: Demande spontanée | U64: l escale | V64: Individuelle | X64: l escale | Y64: Clôturé | Z64: Réorientation
A65: 63 | B65: ouattara | C65: ahmed | D65: Homme | E65: 30 - 50 ans | F65: ADRESSE | H65: =IFERROR(VLOOKUP(F65, Index!C:D, 2, FALSE), "") -> SECTEUR | I65: 0465436003 | K65: Sedia | L65: 45749 | M65: 45749 | N65: =IF(OR(L65="", M65=""), "", IF(L65=M65, 1, M65 - L65)) -> 1 | P65: Autres conflits | Q65: abus de confiance sur personne fragilisé | R65: Demande spontanée | V65: Individuelle | Y65: Clôturé | Z65: Réorientation
A66: 64 | B66: Rawari | C66: Ali | D66: Homme | E66: 30 - 50 ans | F66: Rue des Goujons | G66: 61 | H66: =IFERROR(VLOOKUP(F66, Index!C:D, 2, FALSE), "") -> Cureghem | I66: 0485/789156 | K66: Pascal | L66: 45719 | M66: 45751 | N66: =IF(OR(L66="", M66=""), "", IF(L66=M66, 1, M66 - L66)) -> 32 | O66: 45835 | P66: Conflits de voisinage | Q66: nuisances sonores | R66: Foyer Anderlechtois | T66: Autre | U66: Goujonissimo | V66: Individuelle | Y66: Clôturé | Z66: Refus (de l'une partie ou des deux)
A67: 65 | B67: Chand | C67: Dorothy | D67: Femme | E67: 18 - 30 ans | F67: Rue Polydore Moerman | G67: 33 | H67: =IFERROR(VLOOKUP(F67, Index!C:D, 2, FALSE), "") -> Peterbos | I67: 0472/677733 | K67: Pascal | L67: 45751 | M67: 45751 | N67: =IF(OR(L67="", M67=""), "", IF(L67=M67, 1, M67 - L67)) -> 1 | O67: 45790 | P67: Conflits Locatifs | Q67: refus préavis et dialogue | R67: Autre | S67: Site Internet | T67: ULAC | V67: Individuelle | Y67: Clôturé | Z67: Réorientation
A68: 66 | B68: Malaainine | C68: Amine | D68: Homme | E68: 30 - 50 ans | F68: ADRESSE | H68: =IFERROR(VLOOKUP(F68, Index!C:D, 2, FALSE), "") -> SECTEUR | I68: 0493749617 | J68: amineabdomalaaine@gmail.com | K68: Sedia | L68: 45756 | M68: 45756 | N68: =IF(OR(L68="", M68=""), "", IF(L68=M68, 1, M68 - L68)) -> 1 | P68: Conflits Familiaux/ Conjugaux | R68: Demande spontanée | V68: Individuelle | Y68: Clôturé | Z68: Réorientation
A69: 67 | B69: wathon | C69: cynthia | D69: Femme | E69: 30 - 50 ans | F69: Place de la Beauté | G69: 6 | H69: =IFERROR(VLOOKUP(F69, Index!C:D, 2, FALSE), "") -> Scheut | I69: 0487164506 | K69: Sedia | L69: 45790 | M69: 45790 | N69: =IF(OR(L69="", M69=""), "", IF(L69=M69, 1, M69 - L69)) -> 1 | O69: 45818 | P69: Conflits Locatifs | Q69: impayé | R69: Demande spontanée | V69: Individuelle | Y69: Clôturé | Z69: Interruption du processus de médiation
A70: 68 | B70: Lamsyeh | C70: sofiane | D70: Femme | E70: 30 - 50 ans | F70: rue de neerpede | G70: 382 | H70: =IFERROR(VLOOKUP(F70, Index!C:D, 2, FALSE), "") -> Neerpede | I70: 0486333517 | K70: Sedia | L70: 45791 | M70: 45791 | N70: =IF(OR(L70="", M70=""), "", IF(L70=M70, 1, M70 - L70)) -> 1 | O70: 45783 | P70: Conflits Locatifs | R70: Demande spontanée | V70: Individuelle | Y70: Clôturé | Z70: Impossibilité technique (non-joignables)
A71: 69 | B71: Bouach | C71: Mohammed | D71: Homme | E71: 30 - 50 ans | G71: 262 | H71: =IFERROR(VLOOKUP(F71, Index!C:D, 2, FALSE), "") | I71: 0479659353 | K71: Sedia | L71: 45798 | M71: 45798 | N71: =IF(OR(L71="", M71=""), "", IF(L71=M71, 1, M71 - L71)) -> 1 | P71: Conflits de voisinage | Q71: impayé | R71: Demande spontanée | V71: Individuelle | Y71: Clôturé | Z71: Refus (de l'une partie ou des deux)
A72: 70 | B72: kamtchou | C72: lionel | D72: Homme | E72: 30 - 50 ans | H72: =IFERROR(VLOOKUP(F72, Index!C:D, 2, FALSE), "") | J72: marine.perilleux@cpmswl.be | K72: Sedia | L72: 45800 | M72: 45800 | N72: =IF(OR(L72="", M72=""), "", IF(L72=M72, 1, M72 - L72)) -> 1 | R72: Demande spontanée | V72: Individuelle | Y72: Clôturé
A73: 71 | B73: Chats JP | D73: Femme | E73: 50 ans et + | H73: =IFERROR(VLOOKUP(F73, Index!C:D, 2, FALSE), "") | K73: Pascal | L73: 45811 | M73: 45811 | N73: =IF(OR(L73="", M73=""), "", IF(L73=M73, 1, M73 - L73)) -> 1 | O73: 45811 | P73: Autres conflits | Q73: dettes entretien chatt | R73: Justice de Paix | V73: Individuelle | Y73: Clôturé | Z73: Accord verbal
A74: 72 | B74: Vandervecken | C74: Lucie | D74: Femme | E74: 30 - 50 ans | F74: Rue Edmond Delcourt | G74: 17A | H74: =IFERROR(VLOOKUP(F74, [1]Index!C:D, 2, FALSE), "") -> Scheut | I74: 0476/587336 | K74: Pascal | L74: 45732 | M74: 45755 | N74: =IF(OR(L74="", M74=""), "", IF(L74=M74, 1, M74 - L74)) -> 23 | O74: 45951 | P74: Conflits de voisinage | R74: Demande spontanée | V74: Individuelle | Y74: Clôturé | Z74: Apaisement
A75: 73 | B75: Laaroussi | D75: Homme | E75: 30 - 50 ans | F75: Avenue Nellie Melba | G75: 42 | H75: =IFERROR(VLOOKUP(F75, [1]Index!C:D, 2, FALSE), "") -> Parc | I75: 0489/879860 | K75: Pascal | L75: 45733 | M75: 45762 | N75: =IF(OR(L75="", M75=""), "", IF(L75=M75, 1, M75 - L75)) -> 29 | O75: 45951 | P75: Conflits de voisinage | R75: Autre | S75: Bxl Environnmt | V75: Individuelle | Y75: Clôturé | Z75: Interruption du processus de médiation
A76: 74 | B76: Abi | C76: Rodriguez | D76: Homme | E76: 30 - 50 ans | F76: Square de l'Aviation | H76: =IFERROR(VLOOKUP(F76, [1]Index!C:D, 2, FALSE), "") -> Cureghem | I76: 0478/832986 | K76: Pascal | L76: 45772 | M76: 45790 | N76: =IF(OR(L76="", M76=""), "", IF(L76=M76, 1, M76 - L76)) -> 18 | O76: 45838 | P76: Copropriété | R76: Autre | S76: Bche à oreille | V76: Collective | Y76: Clôturé | Z76: Accord verbal
A77: 75 | B77: Diop | C77: Ndeye | D77: Homme | H77: =IFERROR(VLOOKUP(F77, [1]Index!C:D, 2, FALSE), "") | I77: 0478/048123 | K77: Pascal | L77: 45786 | M77: 45786 | N77: =IF(OR(L77="", M77=""), "", IF(L77=M77, 1, M77 - L77)) -> 1 | O77: 45797 | P77: Conflits de voisinage | R77: CPAS | V77: Individuelle | Y77: Clôturé | Z77: Apaisement avant médiation
A78: 76 | B78: Sadik | C78: Ayman | D78: Homme | F78: Rue Docteur De Meersman | G78: 30 | H78: =IFERROR(VLOOKUP(F78, [1]Index!C:D, 2, FALSE), "") -> Cureghem | I78: 0466/324687 | K78: Pascal | L78: 45784 | M78: 45790 | N78: =IF(OR(L78="", M78=""), "", IF(L78=M78, 1, M78 - L78)) -> 6 | O78: 45798 | P78: Conflits de voisinage | R78: Autre | S78: Echevin Prevt | V78: Collective | Y78: Clôturé | Z78: Refus (de l'une partie ou des deux)
A79: 77 | B79: Camarata | D79: Femme | E79: 50 ans et + | F79: Rue Victor Rauter | G79: 32 | H79: =IFERROR(VLOOKUP(F79, [1]Index!C:D, 2, FALSE), "") -> Vaillance | I79: 0494/070730 | K79: Pascal | L79: 45783 | M79: 45790 | N79: =IF(OR(L79="", M79=""), "", IF(L79=M79, 1, M79 - L79)) -> 7 | O79: 45790 | P79: Conflits de voisinage | R79: Autre | S79: Presidt FA | V79: Individuelle | Y79: Clôturé | Z79: Refus (de l'une partie ou des deux)
A80: 78 | B80: Lawniczak | C80: Marlon | D80: Homme | E80: 30 - 50 ans | F80: Rue d'Aumale | H80: =IFERROR(VLOOKUP(F80, [1]Index!C:D, 2, FALSE), "") -> Vaillance | I80: 0456/752606 | K80: Pascal | L80: 45777 | M80: 45790 | N80: =IF(OR(L80="", M80=""), "", IF(L80=M80, 1, M80 - L80)) -> 13 | O80: 45790 | R80: Demande spontanée | S80: bche à oreille | V80: Individuelle | Y80: Clôturé | Z80: Interruption du processus de médiation
A81: 79 | B81: Van Overstraeten | D81: Homme | E81: 50 ans et + | F81: Rue Delwart | H81: =IFERROR(VLOOKUP(F81, [1]Index!C:D, 2, FALSE), "") -> La Roue | I81: 0477/542777 | K81: Pascal | L81: 45772 | M81: 45790 | N81: =IF(OR(L81="", M81=""), "", IF(L81=M81, 1, M81 - L81)) -> 18 | O81: 45790 | P81: Conflits de voisinage | R81: Déjà venu | V81: Individuelle | Y81: Clôturé | Z81: Impossibilité technique (non-joignables)
A82: 80 | B82: Stoilova | C82: Krasimira | D82: Femme | F82: Avenue de Scheut | G82: 213 | H82: =IFERROR(VLOOKUP(F82, [1]Index!C:D, 2, FALSE), "") -> Scheut | I82: 0478/478830 | K82: Pascal | L82: 45771 | M82: 45790 | N82: =IF(OR(L82="", M82=""), "", IF(L82=M82, 1, M82 - L82)) -> 19 | O82: 45790 | P82: Conflits de voisinage | R82: Demande spontanée | V82: Individuelle | Y82: Clôturé | Z82: Impossibilité technique (non-joignables)
A83: 81 | B83: Franco | D83: Femme | E83: 50 ans et + | F83: Rue de la Justice | G83: 20 | H83: =IFERROR(VLOOKUP(F83, [1]Index!C:D, 2, FALSE), "") -> Vaillance | I83: 0477/272316 | K83: Pascal | L83: 45709 | M83: 45751 | N83: =IF(OR(L83="", M83=""), "", IF(L83=M83, 1, M83 - L83)) -> 42 | O83: 45810 | P83: Conflits de voisinage | R83: Gardiens de la Paix | S83: Belabed | V83: Collective | Y83: Clôturé | Z83: Refus (de l'une partie ou des deux)
A84: 82 | B84: Poitrenaud | C84: Isabelle | D84: Femme | E84: 30 - 50 ans | F84: Rue de la Promenade | G84: 13 | H84: =IFERROR(VLOOKUP(F84, [1]Index!C:D, 2, FALSE), "") -> La Roue | I84: 0478/582359 | K84: Pascal | L84: 45718 | M84: 45720 | N84: =IF(OR(L84="", M84=""), "", IF(L84=M84, 1, M84 - L84)) -> 2 | P84: Conflits de voisinage | R84: Demande spontanée | V84: Individuelle | Y84: En cours
A85: 83 | B85: Akifi | C85: Adil | D85: Homme | E85: 18 - 30 ans | H85: =IFERROR(VLOOKUP(F85, [1]Index!C:D, 2, FALSE), "") | I85: 0488/450335 | K85: Pascal | L85: 45756 | M85: 45786 | N85: =IF(OR(L85="", M85=""), "", IF(L85=M85, 1, M85 - L85)) -> 30 | P85: Copropriété | R85: Autre | S85: CRU | V85: Individuelle | Y85: Clôturé | Z85: Impossibilité technique (non-joignables)
A86: 84 | B86: Amar | D86: Homme | E86: 30 - 50 ans | F86: Rue Van Lint | G86: 10 | H86: =IFERROR(VLOOKUP(F86, [1]Index!C:D, 2, FALSE), "") -> Cureghem | K86: Pascal | L86: 45764 | M86: 45764 | N86: =IF(OR(L86="", M86=""), "", IF(L86=M86, 1, M86 - L86)) -> 1 | O86: 45810 | P86: Conflits de voisinage | R86: Demande spontanée | V86: Individuelle | Y86: Clôturé | Z86: Impossibilité technique (non-joignables)
A87: 85 | B87: Van Hemelrijck | D87: Homme | E87: 30 - 50 ans | F87: Rue de Liverpool | G87: 82 | H87: =IFERROR(VLOOKUP(F87, [1]Index!C:D, 2, FALSE), "") -> Cureghem | I87: 0478/708428 | K87: Pascal | L87: 45751 | M87: 45763 | N87: =IF(OR(L87="", M87=""), "", IF(L87=M87, 1, M87 - L87)) -> 12 | O87: 45813 | P87: Conflits de voisinage | R87: Demande spontanée | S87: Demande spontanée | V87: Individuelle | Y87: Clôturé | Z87: Interruption du processus de médiation
A88: 86 | B88: Simal | C88: Benoît | D88: Homme | E88: 30 - 50 ans | F88: Rue Victor Rauter | G88: 276 | H88: =IFERROR(VLOOKUP(F88, [1]Index!C:D, 2, FALSE), "") -> Vaillance | I88: 0475/836732 | K88: Pascal | L88: 45743 | M88: 45763 | N88: =IF(OR(L88="", M88=""), "", IF(L88=M88, 1, M88 - L88)) -> 20 | O88: 45789 | P88: Conflits de voisinage | R88: Autre | S88: Permis Environnemt | V88: Individuelle | Y88: Clôturé | Z88: Refus (de l'une partie ou des deux)
A89: 87 | B89: Bandas | C89: Sylvia | D89: Femme | E89: 30 - 50 ans | F89: Rue Bara | G89: 85 | H89: =IFERROR(VLOOKUP(F89, [1]Index!C:D, 2, FALSE), "") -> Cureghem | I89: 0468/128150 | K89: Pascal | L89: 45757 | M89: 45761 | N89: =IF(OR(L89="", M89=""), "", IF(L89=M89, 1, M89 - L89)) -> 4 | O89: 45789 | P89: Conflits Locatifs | R89: Justice de Paix | S89: Justice de Paix | V89: Individuelle | Y89: Clôturé | Z89: Réorientation
A90: 88 | B90: Gawrysin | C90: Ana | D90: Femme | E90: 50 ans et + | H90: =IFERROR(VLOOKUP(F90, [1]Index!C:D, 2, FALSE), "") | I90: 0485/840623 | K90: Pascal | L90: 45758 | M90: 45790 | N90: =IF(OR(L90="", M90=""), "", IF(L90=M90, 1, M90 - L90)) -> 32 | O90: 45790 | P90: Conflits de voisinage | R90: Demande spontanée | V90: Individuelle | Y90: Clôturé | Z90: Apaisement avant médiation
A91: 89 | B91: Van Saene | C91: David | D91: Homme | E91: 30 - 50 ans | F91: Avenue Eugène Ysaÿe | G91: 105 | H91: =IFERROR(VLOOKUP(F91, [1]Index!C:D, 2, FALSE), "") -> Parc | I91: 0486/510427 | K91: Pascal | L91: 45735 | M91: 45765 | N91: =IF(OR(L91="", M91=""), "", IF(L91=M91, 1, M91 - L91)) -> 30 | O91: 45790 | P91: Conflits de voisinage | R91: Déjà venu | V91: Individuelle | Y91: Clôturé | Z91: Refus (de l'une partie ou des deux)
A92: 90 | B92: Bachtsevanos | C92: Vacilios | D92: Homme | F92: Avenue Norbert Gille | G92: 70 | H92: =IFERROR(VLOOKUP(F92, [1]Index!C:D, 2, FALSE), "") -> Scheut | J92: basile.bax@gmail.com | K92: Pascal | L92: 45754 | M92: 45793 | N92: =IF(OR(L92="", M92=""), "", IF(L92=M92, 1, M92 - L92)) -> 39 | O92: 45793 | P92: Conflits Locatifs | R92: Demande spontanée | V92: Individuelle | Y92: Clôturé | Z92: Impossibilité technique (non-joignables)
A93: 91 | B93: Brassier | C93: Emilie | D93: Femme | H93: =IFERROR(VLOOKUP(F93, [1]Index!C:D, 2, FALSE), "") | I93: 0493193434 | K93: Pascal | L93: 45730 | M93: 45763 | N93: =IF(OR(L93="", M93=""), "", IF(L93=M93, 1, M93 - L93)) -> 33 | O93: 45763 | P93: Copropriété | R93: Demande spontanée | V93: Individuelle | Y93: Clôturé | Z93: Apaisement avant médiation
A94: 92 | B94: El Bousealiti | D94: Femme | E94: 30 - 50 ans | F94: Rue de la Procession | G94: 40 | H94: =IFERROR(VLOOKUP(F94, [1]Index!C:D, 2, FALSE), "") -> Vaillance | I94: 0484/786593 | K94: Pascal | L94: 45793 | M94: 45793 | N94: =IF(OR(L94="", M94=""), "", IF(L94=M94, 1, M94 - L94)) -> 1 | O94: 45797 | P94: Conflits de voisinage | Q94: Arbre | R94: Autre | S94: Home Grade | V94: Individuelle | W94: Autres | X94: Notaire | Y94: Clôturé | Z94: Réorientation
A95: 93 | B95: Jana | C95: Nordine | D95: Femme | E95: 30 - 50 ans | H95: =IFERROR(VLOOKUP(F95, [1]Index!C:D, 2, FALSE), "") | I95: 0485/529830 | K95: Pascal | L95: 45772 | M95: 45790 | N95: =IF(OR(L95="", M95=""), "", IF(L95=M95, 1, M95 - L95)) -> 18 | O95: 45790 | P95: Autres conflits | Q95: harcèlment lieu du travail | R95: Demande spontanée | S95: bouche à oreille | V95: Individuelle | Y95: Clôturé | Z95: Apaisement avant médiation
A96: 94 | B96: Tassin | C96: Alain | D96: Homme | E96: 30 - 50 ans | H96: =IFERROR(VLOOKUP(F96, [1]Index!C:D, 2, FALSE), "") | I96: 0476/473713 | K96: Pascal | L96: 45758 | M96: 45758 | N96: =IF(OR(L96="", M96=""), "", IF(L96=M96, 1, M96 - L96)) -> 1 | O96: 45775 | P96: Conflits Locatifs | R96: Justice de Paix | V96: Individuelle | Y96: Clôturé | Z96: Refus (de l'une partie ou des deux)
A97: 95 | B97: Boulekwam | D97: Homme | E97: 30 - 50 ans | F97: ADRESSE | H97: =IFERROR(VLOOKUP(F97, Index!C:D, 2, FALSE), "") -> SECTEUR | I97: 0470355471 | K97: Sedia | L97: 45825 | M97: 45825 | N97: =IF(OR(L97="", M97=""), "", IF(L97=M97, 1, M97 - L97)) -> 1 | Y97: En cours
A98: 96 | B98: Vandenhautte | D98: Femme | E98: 50 ans et + | F98: ADRESSE | H98: =IFERROR(VLOOKUP(F98, Index!C:D, 2, FALSE), "") -> SECTEUR | I98: 0486461706 | J98: laurent76bxl@gmail.com | K98: Sedia | L98: 45825 | M98: 45825 | N98: =IF(OR(L98="", M98=""), "", IF(L98=M98, 1, M98 - L98)) -> 1 | O98: 45874 | P98: Conflits de voisinage | Y98: Clôturé | Z98: Refus (de l'une partie ou des deux)
A99: 97 | B99: Robberechts | C99: Sofie | D99: Femme | E99: 30 - 50 ans | F99: Avenue de Scheut | G99: 203 | H99: =IFERROR(VLOOKUP(F99, Index!C:D, 2, FALSE), "") -> Scheut | I99: 0474/432917 | K99: Pascal | L99: 45823 | M99: 45825 | N99: =IF(OR(L99="", M99=""), "", IF(L99=M99, 1, M99 - L99)) -> 2 | O99: 45951 | P99: Conflits de voisinage | R99: Déjà venu | V99: Individuelle | Y99: Clôturé | Z99: Apaisement avant médiation
A100: 98 | B100: Defosse | D100: Homme | E100: 50 ans et + | F100: Rue du Chapeau | G100: 33 | H100: =IFERROR(VLOOKUP(F100, Index!C:D, 2, FALSE), "") -> Cureghem | I100: 0485/863163 | K100: Pascal | L100: 45810 | M100: 45811 | N100: =IF(OR(L100="", M100=""), "", IF(L100=M100, 1, M100 - L100)) -> 1 | O100: 45824 | P100: Conflits de voisinage | R100: Pôle Assuétudes | U100: service soc comensia | V100: Collective | W100: ULAC | Y100: Clôturé | Z100: Réorientation
...

Sheet Synthèse 2025
E2: Synthèse des données statistiques 2025
D6: Nombre de dossiers traités | E6: =COUNT('Liste usagers 2025'!A3:A368) -> 170 | H6: Origine de la demande | J6: Pourcentage | L6: Statut des dossiers | N6: Pourcentage
H7: Collègues Prévention | I7: {=SUM(COUNTIFS('Liste usagers 2025'!R$3:R$834, {"TSR";"CRIPA";"Gardiens de la Paix";"Pôle Assuétudes";"Pôle Jeunesse";"Prévention Vol";"Technoprévention"}))} -> 3 | J7: =I7/$E$6 -> 0.017647059 | L7: En cours | M7: =COUNTIF('Liste usagers 2025'!Y$3:Y834,"En cours") -> 20 | N7: =M7/$E$6 -> 0.11764706
D8: Nombre de dossiers par type de médiation | F8: Pourcentage | H8: Services "Logement" | I8: {=SUM(COUNTIFS('Liste usagers 2025'!R$3:R$834, {"ULAC";"Syndicat des Locataires";"Foyer Anderlechtois";"Comensia"}))} -> 5 | J8: =I8/$E$6 -> 0.029411765 | L8: En attente | M8: =COUNTIF('Liste usagers 2025'!Y$3:Y834,"En attente") -> 3 | N8: =M8/$E$6 -> 0.017647059
D9: Médiation individuelle | E9: =COUNTIF('Liste usagers 2025'!V3:V368, "Individuelle") -> 153 | F9: =IF($E$11=0, 0, E9/$E$11) -> 0.94444444 | H9: Services Judiciaires | I9: {=SUM(COUNTIFS('Liste usagers 2025'!R$3:R$834, {"Justice de Paix";"Police";"Foyer Anderlechtois";"Service de Médiation à la Police"}))} -> 16 | J9: =I9/$E$6 -> 0.094117647 | L9: Clôturé | M9: =COUNTIF('Liste usagers 2025'!Y$3:Y834,"Clôturé") -> 146 | N9: =M9/$E$6 -> 0.85882353
D10: Médiation collective | E10: =COUNTIF('Liste usagers 2025'!V3:V368, "Collective") -> 9 | F10: =IF($E$11=0, 0, E10/$E$11) -> 0.055555556 | H10: Services communaux | I10: {=SUM(COUNTIFS('Liste usagers 2025'!R$3:R$834, {"CPAS";"Service Séniors";"Espaces Verts";"Service Mobilité";"Services de Médiation (autres communes)";"Antenne LISA (Vaillance)";"Antenne LISA (Peterbos)"}))} -> 1 | J10: =I10/$E$6 -> 0.0058823529 | L10: Total | M10: =SUM(M7:M9) -> 169 | N10: =SUM(N7:N9) -> 0.99411765
D11: Total | E11: =SUM(E9:E10) -> 162 | F11: =SUM(F9:F10) -> 1 | H11: Service du secteur associatif | I11: {=SUM(COUNTIFS('Liste usagers 2025'!R$3:R$834, {"PCS Albert";"Cactus";"Service Social de Cureghem";"CAW Westland";"Maison Médicale Horizon";"Maison Médicale Medikuregem"}))} -> 3 | J11: =I11/$E$6 -> 0.017647059
D12: Nombre de dossiers par secteur | F12: Pourcentage | H12: Demande spontanée | I12: =COUNTIF('Liste usagers 2025'!R$3:R834,"Demande spontanée") -> 83 | J12: =I12/$E$6 -> 0.48823529
D13: Cureghem | E13: =COUNTIF('Liste usagers 2025'!$H$3:H871,"Cureghem") -> 28 | F13: =E13/$E$21 -> 0.25925926 | H13: Autres | I13: =COUNTIF('Liste usagers 2025'!R$3:R834,"Autres") -> 0 | J13: =I13/$E$6 -> 0 | L13: Identification | N13: Pourcentage
D14: Industrie | E14: =COUNTIF('Liste usagers 2025'!$H$3:H873,"Industrie") -> 0 | F14: =E14/$E$21 -> 0 | H14: Total | I14: =SUM(I7:I13) -> 111 | J14: =SUM(J7:J13) -> 0.65294118 | L14: Genre
D15: Vaillance | E15: =COUNTIF('Liste usagers 2025'!$H$3:H874,"Vaillance") -> 23 | F15: =E15/$E$21 -> 0.21296296 | L15: Homme | M15: =COUNTIF('Liste usagers 2025'!$D$3:D834,"Homme") -> 69 | N15: =M15/$M$18 -> 0.42857143
D16: Scheut | E16: =COUNTIF('Liste usagers 2025'!$H$3:H875,"Scheut") -> 21 | F16: =E16/$E$21 -> 0.19444444 | H16: Traitement apporté | J16: Pourcentage | L16: Femme | M16: =COUNTIF('Liste usagers 2025'!$D$3:D835,"Femme") -> 92 | N16: =M16/$M$18 -> 0.57142857
D17: Parc | E17: =COUNTIF('Liste usagers 2025'!$H$3:H876,"Parc") -> 14 | F17: =E17/$E$21 -> 0.12962963 | H17: Partenariats/collaborations | L17: X | M17: =COUNTIF('Liste usagers 2025'!$D$3:D836,"X") -> 0 | N17: =M17/$M$18 -> 0
D18: Peterbos | E18: =COUNTIF('Liste usagers 2025'!$H$3:H877,"Peterbos") -> 11 | F18: =E18/$E$21 -> 0.10185185 | H18: Collègues Prévention | I18: {=SUM(COUNTIFS('Liste usagers 2025'!T$3:T$834, {"TSR";"CRIPA";"Gardiens de la Paix";"Pôle Assuétudes";"Pôle Jeunesse";"Prévention Vol";"Technoprévention"}))} -> 9 | J18: =I18/$I$24 -> 0.5625 | L18: Total | M18: =SUM(M15:M17) -> 161 | N18: =SUM(N15:N17) -> 1
D19: La Roue | E19: =COUNTIF('Liste usagers 2025'!$H$3:H878,"La Roue") -> 8 | F19: =E19/$E$21 -> 0.074074074 | H19: Services "Logement" | I19: {=SUM(COUNTIFS('Liste usagers 2025'!T$3:T$834, {"ULAC";"Syndicat des Locataires";"Foyer Anderlechtois";"Comensia"}))} -> 1 | J19: =I19/$I$24 -> 0.0625 | L19: Tranche d'âge
D20: Neerpede | E20: =COUNTIF('Liste usagers 2025'!$H$3:H879,"Neerpede") -> 3 | F20: =E20/$E$21 -> 0.027777778 | H20: Services Judiciaires | I20: {=SUM(COUNTIFS('Liste usagers 2025'!T$3:T$834, {"Justice de Paix";"Police";"Foyer Anderlechtois";"Service de Médiation à la Police"}))} -> 5 | J20: =I20/$I$24 -> 0.3125 | L20: < 18 ans | M20: =COUNTIF('Liste usagers 2025'!$E$3:E834,"Moins de 18 ans") -> 0 | N20: =IF($M$24=0, 0, M20/$M$24) -> 0
D21: Total | E21: =SUM(E13:E20) -> 108 | F21: =E21/$E$21 -> 1 | H21: Services communaux | I21: {=SUM(COUNTIFS('Liste usagers 2025'!T$3:T$834, {"CPAS";"Service Séniors";"Espaces Verts";"Service Mobilité";"Services de Médiation (autres communes)";"Antenne LISA (Vaillance)";"Antenne LISA (Peterbos)"}))} -> 0 | J21: =I21/$I$24 -> 0 | L21: 18 - 30 ans | M21: =COUNTIF('Liste usagers 2025'!$E$3:$E$834,"18 - 30 ans") -> 7 | N21: =IF($M$24=0, 0, M21/$M$24) -> 0.04964539
H22: Service du secteur associatif | I22: {=SUM(COUNTIFS('Liste usagers 2025'!T$3:T$834, {"PCS Albert";"Cactus";"Service Social de Cureghem";"CAW Westland";"Maison Médicale Horizon";"Maison Médicale Medikuregem"}))} -> 1 | J22: =I22/$I$24 -> 0.0625 | L22: 30 - 50 ans | M22: =COUNTIF('Liste usagers 2025'!$E$3:$E$834,"30 - 50 ans") -> 91 | N22: =IF($M$24=0, 0, M22/$M$24) -> 0.64539007
D23: Type de conflis traités | F23: Pourcentage | H23: Autres | I23: =COUNTIF('Liste usagers 2025'!R$3:R$834,"Autres") -> 0 | J23: =I23/$I$24 -> 0 | L23: 50 ans et + | M23: =COUNTIF('Liste usagers 2025'!$E$3:E834,"50 ans et +") -> 43 | N23: =IF($M$24=0, 0, M23/$M$24) -> 0.30496454
D24: Conflits de voisinage | E24: =COUNTIF('Liste usagers 2025'!P$3:P834,"Conflits de voisinage") -> 82 | F24: =E24/$E$6 -> 0.48235294 | H24: Total | I24: =SUM(I18:I23) -> 16 | J24: =I24/$I$24 -> 1 | L24: Total | M24: =SUM(M20:M23) -> 141 | N24: =SUM(N20:N23) -> 1
D25: Conflits riverains/Horeca | E25: =COUNTIF('Liste usagers 2025'!P$3:P834,"Conflits riverains/HORECA") -> 0 | F25: =E25/$E$6 -> 0 | H25: Orientation
D26: Conflits familiaux/conjugaux | E26: =COUNTIF('Liste usagers 2025'!P$3:P834,"Conflits familiaux/ Conjugaux") -> 16 | F26: =E26/$E$6 -> 0.094117647 | H26: Collègues Prévention | I26: {=SUM(COUNTIFS('Liste usagers 2025'!W$3:W$834, {"TSR";"CRIPA";"Gardiens de la Paix";"Pôle Assuétudes";"Pôle Jeunesse";"Prévention Vol";"Technoprévention"}))} -> 10 | J26: =I26/$E$6 -> 0.058823529
D27: Conflits locatifs | E27: =COUNTIF('Liste usagers 2025'!P$3:P834,"Conflits locatifs") -> 31 | F27: =E27/$E$6 -> 0.18235294 | H27: Services "Logement" | I27: {=SUM(COUNTIFS('Liste usagers 2025'!W$3:W$834, {"ULAC";"Syndicat des Locataires";"Foyer Anderlechtois";"Comensia"}))} -> 1 | J27: =I27/$E$6 -> 0.0058823529
D28: Copropriété | E28: =COUNTIF('Liste usagers 2025'!P$3:P834,"Copropriété") -> 12 | F28: =E28/$E$6 -> 0.070588235 | H28: Services Judiciaires | I28: {=SUM(COUNTIFS('Liste usagers 2025'!R$3:R$834, {"Justice de Paix";"Police";"Foyer Anderlechtois";"Service de Médiation à la Police"}))} -> 16 | J28: =I28/$E$6 -> 0.094117647
D29: Conflits en lien avec l'espace public | E29: =COUNTIF('Liste usagers 2025'!P$3:P834,"Conflits en lien avec l'espace public") -> 1 | F29: =E29/$E$6 -> 0.0058823529 | H29: Services communaux | I29: {=SUM(COUNTIFS('Liste usagers 2025'!W$3:W$834, {"CPAS";"Service Séniors";"Espaces Verts";"Service Mobilité";"Services de Médiation (autres communes)";"Antenne LISA (Vaillance)";"Antenne LISA (Peterbos)"}))} -> 0 | J29: =I29/$E$6 -> 0
D30: Cohabitation/Colocation | E30: =COUNTIF('Liste usagers 2025'!P$3:P834,"Cohabitation/Colocation") -> 1 | F30: =E30/$E$6 -> 0.0058823529 | H30: Service du secteur associatif | I30: {=SUM(COUNTIFS('Liste usagers 2025'!W$3:W$834, {"PCS Albert";"Cactus";"Service Social de Cureghem";"CAW Westland";"Maison Médicale Horizon";"Maison Médicale Medikuregem"}))} -> 1 | J30: =I30/$E$6 -> 0.0058823529
D31: Autres conflits | E31: =COUNTIF('Liste usagers 2025'!P$3:P834,"Autres conflits") -> 19 | F31: =E31/$E$6 -> 0.11176471 | H31: Autres | I31: =COUNTIF('Liste usagers 2025'!W$3:W834,"Autres") -> 1 | J31: =I31/$E$6 -> 0.0058823529
D32: Total | E32: =SUM(E24:E31) -> 162 | F32: =SUM(F24:F31) -> 0.95294118 | H32: Total | I32: =SUM(I26:I31) -> 29 | J32: =SUM(J26:J31) -> 0.17058824
H33: Issue de l'intervention
H34: Impossibilité technique (non-joignables) | I34: =COUNTIF('Liste usagers 2025'!Z$3:Z834,"Impossibilité technique (non-joignables)") -> 27 | J34: =I34/$I$41 -> 0.21259843
H35: Refus (de l'une ou des deux parties) | I35: =COUNTIF('Liste usagers 2025'!Z$3:Z834,"Refus (de l'une partie ou des deux)") -> 31 | J35: =I35/$I$41 -> 0.24409449
H36: Réorientation | I36: =COUNTIF('Liste usagers 2025'!Z$3:Z834,"Réorientation") -> 41 | J36: =I36/$I$41 -> 0.32283465
H37: Interruption du processus de médiation | I37: =COUNTIF('Liste usagers 2025'!Z$3:Z834,"Interruption du processus de médiation") -> 11 | J37: =I37/$I$41 -> 0.086614173
H38: Apaisement | I38: =COUNTIF('Liste usagers 2025'!Z$3:Z834,"Apaisement") -> 6 | J38: =I38/$I$41 -> 0.047244094
H39: Accord écrit | I39: =COUNTIF('Liste usagers 2025'!Z$3:Z834,"Accord écrit") -> 2 | J39: =I39/$I$41 -> 0.015748031
H40: Accord verbal | I40: =COUNTIF('Liste usagers 2025'!Z$3:Z834,"Accord verbal") -> 9 | J40: =I40/$I$41 -> 0.070866142
H41: Total | I41: =SUM(I34:I40) -> 127 | J41: =SUM(J34:J40) -> 1

Sheet Index
A1: Tranche d'âge | C1: ADRESSE | D1: SECTEUR
A2: Moins de 18 ans | C2: Rue Raymond van Der Bruggen CPAS | D2: Adresse de référence
A3: 18 - 30 ans | C3: Avenue Clemenceau | D3: Cureghem
A4: 30 - 50 ans | C4: Avenue Clémenceau | D4: Cureghem
A5: 50 ans et + | C5: Boulevard Poincaré | D5: Cureghem
C6: Chaussée de Mons 1-153/2-154 | D6: Cureghem
C7: Clos de la Petite Senne | D7: Cureghem
C8: Clos de l'Équerre | D8: Cureghem
C9: Place Alphonse Lemmens | D9: Cureghem
A10: Genre | C10: Place Bara | D10: Cureghem
A11: Homme | C11: Rue Abbé Cuylits | D11: Cureghem
A12: Femme | C12: Rue Bissé | D12: Cureghem
A13: Non binaire | C13: Rue Brogniez | D13: Cureghem
C14: Rue Broyère | D14: Cureghem
C15: Rue de la Bougie | D15: Cureghem
A16: Type de médiation | C16: Rue de la Clinique | D16: Cureghem
A17: Individuelle | C17: Rue de la Poterie | D17: Cureghem
A18: Collective | C18: Rue de la Rosée | D18: Cureghem
C19: Rue de l'Autonomie | D19: Cureghem
A20: Envoyeurs/Partenaires | C20: Rue de Liverpool | D20: Cureghem
A21: Antenne LISA (Peterbos) | C21: Rue des Matériaux | D21: Cureghem
A22: Antenne LISA (Vaillance) | C22: Rue des Mégissiers | D22: Cureghem
A23: Cactus | C23: Rue Docteur De Meersman | D23: Cureghem
A24: CAW Westland | C24: Rue du Chimiste | D24: Cureghem
A25: Comensia | C25: Rue du Compas | D25: Cureghem
A26: CPAS | C26: Rue Foppens | D26: Cureghem
A27: CRIPA | C27: Rue Gheude | D27: Cureghem
A28: Déjà venu | C28: Rue Haberman | D28: Cureghem
A29: Demande spontanée | C29: Rue Heyvaert | D29: Cureghem
A30: Espaces Verts | C30: Rue Jules Ruhl | D30: Cureghem
A31: Foyer Anderlechtois | C31: Rue Lambert Crickx | D31: Cureghem
... A50: Autre | C50: Place du Conseil | D50: Cureghem
C51: Place Grisar | D51: Cureghem
C52: Place Jorez | D52: Cureghem
C53: Rue Auguste Gevaert | D53: Cureghem
C54: Rue Bara | D54: Cureghem
C55: Rue Charles Parenté | D55: Cureghem
C56: Rue Chomé-Wyns | D56: Cureghem
C57: Rue de Fiennes | D57: Cureghem
C58: Rue de l'Ecole Moderne | D58: Cureghem
C59: Rue de l'Electricité | D59: Cureghem
C60: Rue de l'Instruction | D60: Cureghem
C61: Rue des Bassins | D61: Cureghem
C62: Rue des Deux Gares | D62: Cureghem
... C527: Rue du Chapelain | D527: Vaillance
